odoo/addons/website_apps_store/README.rst
odoo/addons/website_apps_store/__init__.py
odoo/addons/website_apps_store/__manifest__.py
odoo/addons/website_apps_store/controllers/__init__.py
odoo/addons/website_apps_store/controllers/main.py
odoo/addons/website_apps_store/demo/product_template_demo.xml
odoo/addons/website_apps_store/i18n/hr.po
odoo/addons/website_apps_store/i18n/it.po
odoo/addons/website_apps_store/i18n/website_apps_store.pot
odoo/addons/website_apps_store/models/__init__.py
odoo/addons/website_apps_store/models/product.py
odoo/addons/website_apps_store/models/product_template.py
odoo/addons/website_apps_store/readme/CONTRIBUTORS.rst
odoo/addons/website_apps_store/readme/DESCRIPTION.rst
odoo/addons/website_apps_store/readme/ROADMAP.rst
odoo/addons/website_apps_store/static/description/icon.png
odoo/addons/website_apps_store/static/description/index.html
odoo/addons/website_apps_store/static/src/css/main.scss
odoo/addons/website_apps_store/static/src/js/website_apps_store_tour.js
odoo/addons/website_apps_store/static/src/js/website_sale.js
odoo/addons/website_apps_store/tests/__init__.py
odoo/addons/website_apps_store/tests/test_tour_website_apps_store.py
odoo/addons/website_apps_store/tests/test_website_apps_store.py
odoo/addons/website_apps_store/views/assets.xml
odoo/addons/website_apps_store/views/templates.xml
odoo12_addon_website_apps_store-12.0.1.1.1.dist-info/METADATA
odoo12_addon_website_apps_store-12.0.1.1.1.dist-info/WHEEL
odoo12_addon_website_apps_store-12.0.1.1.1.dist-info/top_level.txt
odoo12_addon_website_apps_store-12.0.1.1.1.dist-info/RECORD
