Metadata-Version: 2.1
Name: odoo12-addon-website-apps-store
Version: 12.0.1.1.1
Summary: Website Apps Store
Home-page: https://github.com/OCA/apps-store
Author: Odoo Community Association (OCA), BizzAppDev
Author-email: support@odoo-community.org
License: AGPL-3
Platform: UNKNOWN
Classifier: Programming Language :: Python
Classifier: Framework :: Odoo
Classifier: License :: OSI Approved :: GNU Affero General Public License v3
Requires-Python: >=3.5
Requires-Dist: odoo12-addon-apps-download
Requires-Dist: odoo12-addon-apps-product-creator
Requires-Dist: odoo12-addon-website-form-recaptcha
Requires-Dist: odoo (<12.1dev,>=12.0a)
